{
 "distances":{
     "Hertzelia":[
         
        {"name":"Hertzelia", "distance":0},
        {"name":"Jerusalem", "distance": 345},
        {"name":"Meitar", "distance":76},
        {"name":"Migron", "distance":982}
 ],
     "Jerusalem":[
         
        {"name":"Hertzelia", "distance":345},
        {"name":"Jerusalem", "distance": 0},
        {"name":"Meitar", "distance":476},
        {"name":"Migron", "distance":938}
 ],
     "Meitar":[
         
        {"name":"Hertzelia", "distance":76},
        {"name":"Jerusalem", "distance": 476},
        {"name":"Meitar", "distance":0},
        {"name":"Migron", "distance":98}
 ],
     "Migron":[
         
        {"name":"Hertzelia", "distance":982},
        {"name":"Jerusalem", "distance": 938},
        {"name":"Meitar", "distance":98},
        {"name":"Migron", "distance":0}
 ]
 }   
}